[
    {
        "imdb_id": "tt0120589",
        "origin_country": [
            "BR"
        ],
        "original_language": "pt",
        "original_title": "Predestinado: Arigó e o Espírito do Dr. Fritz",
        "overview": "José Pedro de Freitas, better known as Zé Arigó, was a simple man who lived with his wife Arlete in Congonhas, Minas Gerais. During the 1950s, a time when Spiritism was not as well known and respected in the country, Arigó became a symbol of hope through his surgeries and spiritual cures. Based on a true story, Arigó, with the help of the spirit of Dr. Fritz, performed numerous spiritual surgeries on people from Brazil and the world.",
        "spoken_languages": [
            {
                "english_name": "Portuguese",
                "iso_639_1": "pt",
                "name": "Português"
            }
        ]
    },
    {
        "imdb_id": "tt0173042",
        "origin_country": [
            "IN"
        ],
        "original_language": "kn",
        "original_title": "Premaloka",
        "overview": "Ravichandran tries to woo a classmate. On being spurned, he poses as a mysterious biker and sweeps her off her feet.",
        "spoken_languages": [
            {
                "english_name": "Kannada",
                "iso_639_1": "kn",
                "name": "?????"
            },
            {
                "english_name": "Tamil",
                "iso_639_1": "ta",
                "name": "தமிழ்"
            }
        ]
    }
]